AUTHORS.rst
CONTRIBUTING.rst
HISTORY.rst
LICENSE
MANIFEST.in
README.rst
requirements.txt
setup.cfg
setup.py
aiopb/__init__.py
aiopb/aiopb.py
aiopb/cli.py
aiopb.egg-info/PKG-INFO
aiopb.egg-info/SOURCES.txt
aiopb.egg-info/dependency_links.txt
aiopb.egg-info/entry_points.txt
aiopb.egg-info/not-zip-safe
aiopb.egg-info/requires.txt
aiopb.egg-info/top_level.txt
docs/Makefile
docs/authors.rst
docs/conf.py
docs/contributing.rst
docs/history.rst
docs/index.rst
docs/installation.rst
docs/make.bat
docs/readme.rst
docs/usage.rst
tests/test_aiopb.py
tests/test_main.py