Metadata-Version: 1.1
Name: aiopb
Version: 0.1.7
Summary: Async Pub/Sub
Home-page: https://github.com/asteriogonzalez/aiopb
Author: Asterio
Author-email: asterio.gonzalez@gmail.com
License: MIT license
Keywords: aiopb
Platform: UNKNOWN
Classifier: Development Status :: 2 - Pre-Alpha
Classifier: Intended Audience :: Developers
Classifier: License :: OSI Approved :: MIT License
Classifier: Natural Language :: English
Classifier: Programming Language :: Python :: 2
Classifier: Programming Language :: Python :: 2.7
Classifier: Programming Language :: Python :: 3
Classifier: Programming Language :: Python :: 3.4
Classifier: Programming Language :: Python :: 3.5
Classifier: Programming Language :: Python :: 3.6
Classifier: Programming Language :: Python :: 3.7
